quantumseeding/__init__.py
quantumseeding-0.0.5.dist-info/LICENSE
quantumseeding-0.0.5.dist-info/METADATA
quantumseeding-0.0.5.dist-info/WHEEL
quantumseeding-0.0.5.dist-info/top_level.txt
quantumseeding-0.0.5.dist-info/RECORD
