Metadata-Version: 2.1
Name: quantumseeding
Version: 0.0.5
Summary: Generate really random seeds with Quantum Computers
Author: Josh XT
Author-email: josh@devxt.com
Requires-Python: >=3.10
License-File: LICENSE
Requires-Dist: qiskit
